ryfi/__init__.py
ryfi/main.py
ryfi-2026.1.13.2.dist-info/METADATA
ryfi-2026.1.13.2.dist-info/WHEEL
ryfi-2026.1.13.2.dist-info/entry_points.txt
ryfi-2026.1.13.2.dist-info/top_level.txt
ryfi-2026.1.13.2.dist-info/RECORD
