Metadata-Version: 2.4
Name: ryfi
Version: 2026.1.13.2
Summary: Rybby's Python tools.
Author-email: rybby <rybby@163.com>
Project-URL: Homepage, http://rymaa.cn
Classifier: Environment :: WebAssembly :: WASI
Requires-Python: >=3.8
Provides-Extra: test
Provides-Extra: dev
